{"stats":{"minecraft:custom":{"minecraft:time_since_rest":66018,"minecraft:sprint_one_cm":90280,"minecraft:damage_taken":240,"minecraft:walk_one_cm":108739,"minecraft:drop":5,"minecraft:fly_one_cm":1141061,"minecraft:crouch_one_cm":16178,"minecraft:play_one_minute":147699,"minecraft:deaths":3,"minecraft:sneak_time":10204,"minecraft:jump":637,"minecraft:walk_on_water_one_cm":157,"minecraft:leave_game":3,"minecraft:time_since_death":65996},"minecraft:dropped":{"minecraft:purple_terracotta":1,"minecraft:bricks":1,"minecraft:black_concrete":1,"minecraft:tripwire_hook":1,"minecraft:item_frame":1},"minecraft:used":{"minecraft:dark_oak_stairs":51,"minecraft:trident":1,"minecraft:diorite":1,"minecraft:black_concrete":5,"minecraft:nether_brick_wall":5,"minecraft:bricks":816,"minecraft:sandstone_stairs":5,"minecraft:light_gray_concrete":8,"minecraft:quartz_slab":148,"minecraft:command_block":1,"minecraft:red_wool":8,"minecraft:smooth_quartz_slab":5,"minecraft:grass_block":49,"minecraft:armor_stand":25,"minecraft:string":5,"minecraft:brick_stairs":62,"minecraft:smooth_sandstone":85,"minecraft:quartz_block":417,"minecraft:dark_oak_slab":166,"minecraft:stone":75,"minecraft:quartz_stairs":11,"minecraft:player_head":9,"minecraft:smooth_sandstone_stairs":1,"minecraft:item_frame":48,"minecraft:bedrock":2,"minecraft:debug_stick":40,"minecraft:dark_oak_trapdoor":6,"minecraft:yellow_terracotta":15,"minecraft:cut_sandstone_slab":10,"minecraft:white_banner":2,"minecraft:brick_slab":899,"minecraft:acacia_leaves":26,"minecraft:white_stained_glass":1,"minecraft:sponge":29,"minecraft:crossbow":6,"minecraft:nether_brick_slab":10,"minecraft:glass_pane":154,"minecraft:repeating_command_block":2,"minecraft:purple_terracotta":1,"minecraft:infested_stone_bricks":32,"minecraft:nether_brick_stairs":10,"minecraft:polished_diorite":9}},"DataVersion":2586}